{
  "isAvailableForNewContent" : true,
  "templateType" : 18,
  "attachedStylesheets" : [ ],
  "attachedJs" : [ ],
  "customHead" : "",
  "customFooter" : "",
  "bodyClass" : "",
  "bodyCss" : "",
  "bodyEditable" : false,
  "layoutData" : {
    "x" : 0,
    "w" : 12,
    "name" : "",
    "label" : "",
    "type" : "cell",
    "params" : { },
    "rows" : [ {
      "0" : {
        "x" : 0,
        "w" : 12,
        "name" : "module_1600260851451190",
        "label" : "Page Center",
        "type" : "cell",
        "params" : {
          "css_class" : "page-center",
          "css_id" : "",
          "css_id_str" : "",
          "css_style" : "",
          "overrideable" : false,
          "per_widget_wrapper_html" : "",
          "wrapping_html" : ""
        },
        "rows" : [ {
          "0" : {
            "x" : 0,
            "w" : 12,
            "name" : "module_1600260851451191",
            "label" : "Vertical Inner",
            "type" : "cell",
            "params" : {
              "css_class" : "vertical-inner",
              "css_id" : "",
              "css_id_str" : "",
              "css_style" : "",
              "overrideable" : false,
              "per_widget_wrapper_html" : "",
              "wrapping_html" : ""
            },
            "rows" : [ {
              "0" : {
                "x" : 0,
                "w" : 6,
                "name" : "module_1600260851451192",
                "label" : "Item",
                "type" : "cell",
                "params" : {
                  "css_class" : "vertical-item",
                  "css_id" : "",
                  "css_id_str" : "",
                  "css_style" : "",
                  "overrideable" : false,
                  "per_widget_wrapper_html" : "",
                  "wrapping_html" : ""
                },
                "rows" : [ {
                  "0" : {
                    "x" : 0,
                    "w" : 12,
                    "name" : "module_1600260851451193",
                    "label" : "Vertical Text",
                    "type" : "custom_widget",
                    "params" : {
                      "css_class" : "it-text",
                      "css_id" : "",
                      "css_id_str" : "",
                      "css_style" : "",
                      "html" : "<h2>Pre-designed <br>function libraries</h2>\n<p>No need to put everything in the system. Snap everything into place with pre-built roles and job descriptions based on real-world functions from other companies. Functionly fills in the gaps so you can assign with the click of a button.</p>",
                      "overrideable" : false,
                      "path" : "@hubspot/rich_text",
                      "per_widget_wrapper_html" : "",
                      "schema_version" : 2,
                      "widget_name" : "Rich Text",
                      "wrapping_html" : ""
                    },
                    "rows" : [ ],
                    "rowMetaData" : [ ],
                    "cells" : [ ],
                    "cssId" : "",
                    "cssClass" : "",
                    "cssStyle" : "",
                    "styles" : null,
                    "widgets" : [ ]
                  }
                }, {
                  "0" : {
                    "x" : 0,
                    "w" : 12,
                    "name" : "module_1600260851451194",
                    "label" : "Call-to-Action",
                    "type" : "custom_widget",
                    "params" : {
                      "css_class" : "it-cta cta-purple",
                      "css_id" : "",
                      "css_id_str" : "",
                      "css_style" : "",
                      "guid" : "f27fff8e-b438-4d63-8009-704be298d3c5",
                      "overrideable" : false,
                      "path" : "@hubspot/cta",
                      "per_widget_wrapper_html" : "",
                      "schema_version" : 2,
                      "widget_name" : "Call-to-Action",
                      "wrapping_html" : ""
                    },
                    "rows" : [ ],
                    "rowMetaData" : [ ],
                    "cells" : [ ],
                    "cssId" : "",
                    "cssClass" : "",
                    "cssStyle" : "",
                    "styles" : null,
                    "widgets" : [ ]
                  }
                } ],
                "rowMetaData" : [ ],
                "cells" : [ ],
                "cssId" : "",
                "cssClass" : "",
                "cssStyle" : "",
                "styles" : null,
                "widgets" : [ ]
              },
              "6" : {
                "x" : 6,
                "w" : 6,
                "name" : "module_1600260851451195",
                "label" : "Item",
                "type" : "cell",
                "params" : {
                  "css_class" : "vertical-item",
                  "css_id" : "",
                  "css_id_str" : "",
                  "css_style" : "",
                  "overrideable" : false,
                  "per_widget_wrapper_html" : "",
                  "wrapping_html" : ""
                },
                "rows" : [ {
                  "0" : {
                    "x" : 0,
                    "w" : 12,
                    "name" : "module_1607416655029141",
                    "label" : "Image or Video",
                    "type" : "custom_widget",
                    "params" : {
                      "css_class" : "it-img",
                      "css_id" : "",
                      "css_id_str" : "",
                      "css_style" : "",
                      "overrideable" : false,
                      "path" : "/Image or Video",
                      "per_widget_wrapper_html" : "",
                      "schema_version" : 2,
                      "widget_name" : "Image or Video",
                      "wrapping_html" : ""
                    },
                    "rows" : [ ],
                    "rowMetaData" : [ ],
                    "cells" : [ ],
                    "cssId" : "",
                    "cssClass" : "",
                    "cssStyle" : "",
                    "styles" : null,
                    "widgets" : [ ]
                  }
                } ],
                "rowMetaData" : [ ],
                "cells" : [ ],
                "cssId" : "",
                "cssClass" : "",
                "cssStyle" : "",
                "styles" : null,
                "widgets" : [ ]
              }
            } ],
            "rowMetaData" : [ ],
            "cells" : [ ],
            "cssId" : "",
            "cssClass" : "",
            "cssStyle" : "",
            "styles" : null,
            "widgets" : [ ]
          }
        } ],
        "rowMetaData" : [ ],
        "cells" : [ ],
        "cssId" : "",
        "cssClass" : "",
        "cssStyle" : "",
        "styles" : null,
        "widgets" : [ ]
      }
    } ],
    "rowMetaData" : [ ],
    "cells" : [ ],
    "cssId" : "",
    "cssClass" : "",
    "cssStyle" : "",
    "styles" : null,
    "widgets" : [ ]
  }
}